agenttobenamed/__init__.py
agenttobenamed/agent.py
agenttobenamed/code_manipulation.py
agenttobenamed/llms.py
agenttobenamed/logger.py
agenttobenamed/prompts.py
agenttobenamed-0.1.14.dist-info/METADATA
agenttobenamed-0.1.14.dist-info/WHEEL
agenttobenamed-0.1.14.dist-info/RECORD
